{
    "week": 6,
    "byes": ["Houston Texans", "Minnesota Vikings"],
    "games": [
      {"id": 601, "a": "Philadelphia Eagles", "h": "New York Giants", "dt": "2025-10-09T20:15:00Z", "stadium": "MetLife Stadium"},
      {"id": 602, "a": "Denver Broncos", "h": "New York Jets", "dt": "2025-10-12T09:30:00Z", "stadium": "Tottenham Hotspur Stadium"},
      {"id": 603, "a": "Los Angeles Rams", "h": "Baltimore Ravens", "dt": "2025-10-12T13:00:00Z", "stadium": "M&T Bank Stadium"},
      {"id": 604, "a": "Dallas Cowboys", "h": "Carolina Panthers", "dt": "2025-10-12T13:00:00Z", "stadium": "Bank of America Stadium"},
      {"id": 605, "a": "Arizona Cardinals", "h": "Indianapolis Colts", "dt": "2025-10-12T13:00:00Z", "stadium": "Lucas Oil Stadium"},
      {"id": 606, "a": "Seattle Seahawks", "h": "Jacksonville Jaguars", "dt": "2025-10-12T13:00:00Z", "stadium": "EverBank Stadium"},
      {"id": 607, "a": "Los Angeles Chargers", "h": "Miami Dolphins", "dt": "2025-10-12T13:00:00Z", "stadium": "Hard Rock Stadium"},
      {"id": 608, "a": "Cleveland Browns", "h": "Pittsburgh Steelers", "dt": "2025-10-12T13:00:00Z", "stadium": "Acrisure Stadium"},
      {"id": 609, "a": "San Francisco 49ers", "h": "Tampa Bay Buccaneers", "dt": "2025-10-12T13:00:00Z", "stadium": "Raymond James Stadium"},
      {"id": 610, "a": "Tennessee Titans", "h": "Las Vegas Raiders", "dt": "2025-10-12T16:05:00Z", "stadium": "Allegiant Stadium"},
      {"id": 611, "a": "Cincinnati Bengals", "h": "Green Bay Packers", "dt": "2025-10-12T16:25:00Z", "stadium": "Lambeau Field"},
      {"id": 612, "a": "New England Patriots", "h": "New Orleans Saints", "dt": "2025-10-12T16:25:00Z", "stadium": "Caesars Superdome"},
      {"id": 613, "a": "Detroit Lions", "h": "Kansas City Chiefs", "dt": "2025-10-12T20:20:00Z", "stadium": "Arrowhead Stadium"},
      {"id": 614, "a": "Buffalo Bills", "h": "Atlanta Falcons", "dt": "2025-10-13T19:15:00Z", "stadium": "Mercedes-Benz Stadium"},
      {"id": 615, "a": "Chicago Bears", "h": "Washington Commanders", "dt": "2025-10-13T20:15:00Z", "stadium": "Northwest Stadium"}
    ]
  }